scrapy_downloaddelay/__init__.py
scrapy_downloaddelay/plugin.py
scrapy_downloaddelay-0.0.1.dist-info/LICENSE
scrapy_downloaddelay-0.0.1.dist-info/METADATA
scrapy_downloaddelay-0.0.1.dist-info/WHEEL
scrapy_downloaddelay-0.0.1.dist-info/entry_points.txt
scrapy_downloaddelay-0.0.1.dist-info/top_level.txt
scrapy_downloaddelay-0.0.1.dist-info/RECORD
