Metadata-Version: 2.1
Name: scrapy-downloaddelay
Version: 0.0.1
Summary: scrapy downloaddelay plugin
Home-page: UNKNOWN
Author: UNKNOWN
Author-email: UNKNOWN
License: UNKNOWN
Platform: UNKNOWN
